ninja_oauth2/__init__.py
ninja_oauth2/main.py
ninja_oauth2/py.typed
ninja_oauth2/openapi/__init__.py
ninja_oauth2/openapi/docs.py
ninja_oauth2/openapi/urls.py
ninja_oauth2/openapi/utils.py
ninja_oauth2/openapi/views.py
ninja_oauth2/security/__init__.py
ninja_oauth2/security/oauth2.py
ninja_oauth2/templates/ninja_oauth2/oauth2-redirect.html
ninja_oauth2/templates/ninja_oauth2/swagger_cdn.html
django_ninja_oauth2-0.1.6.dist-info/METADATA
django_ninja_oauth2-0.1.6.dist-info/WHEEL
django_ninja_oauth2-0.1.6.dist-info/licenses/LICENSE
django_ninja_oauth2-0.1.6.dist-info/RECORD
