Metadata-Version: 2.4
Name: django-ninja-oauth2
Version: 0.1.6
Summary: Django Ninja OAuth2 package enables support of OAuth2 / OpenID Connect Authorization Code Flow for your swagger documentation.
Project-URL: Homepage, https://github.com/EomapCompany/django-ninja-oauth2
Project-URL: Repository, https://github.com/EomapCompany/django-ninja-oauth2
Project-URL: Documentation, https://github.com/EomapCompany/django-ninja-oauth2#readme
Project-URL: Issues, https://github.com/EomapCompany/django-ninja-oauth2/issues
Author-email: "Marcel Siegmann, EOMAP" <siegmann@eomap.de>
License-Expression: MIT
License-File: LICENSE
Keywords: authentication,django,ninja,oauth2,openapi,openid-connect,swagger
Classifier: Development Status :: 4 - Beta
Classifier: Framework :: Django
Classifier: Framework :: Django :: 3.2
Classifier: Framework :: Django :: 4
Classifier: Framework :: Django :: 5
Classifier: Intended Audience :: Developers
Classifier: License :: OSI Approved :: MIT License
Classifier: Programming Language :: Python
Classifier: Programming Language :: Python :: 3
Classifier: Programming Language :: Python :: 3 :: Only
Classifier: Programming Language :: Python :: 3.10
Classifier: Programming Language :: Python :: 3.11
Classifier: Programming Language :: Python :: 3.12
Classifier: Topic :: Internet :: WWW/HTTP
Classifier: Topic :: Software Development :: Libraries :: Python Modules
Requires-Python: >=3.10
Requires-Dist: django-ninja>=1.1.0
Requires-Dist: pyjwt[crypto]>=2.10.1
Requires-Dist: requests>=2.32.5
